manim_fa_physics/__init__.py
manim_fa_physics/electrostatics.py
manim_fa_physics/lenses.py
manim_fa_physics/magnetostatics.py
manim_fa_physics/mechanics.py
manim_fa_physics/pendulum.py
manim_fa_physics/rays.py
manim_fa_physics-0.1.0.dist-info/licenses/LICENSE
manim_fa_physics-0.1.0.dist-info/METADATA
manim_fa_physics-0.1.0.dist-info/WHEEL
manim_fa_physics-0.1.0.dist-info/top_level.txt
manim_fa_physics-0.1.0.dist-info/RECORD
