Metadata-Version: 2.4
Name: manim-fa-physics
Version: 0.1.0
Summary: افزونه فیزیک برای Manim (مکانیک، گرانش، اوپتیک، الکترومغناطیس، الکترواستاتیک)
Home-page: https://github.com/Tabesh2020/manim-fa-physics
Author: Tabesh Alli
License: MIT
Classifier: Programming Language :: Python :: 3
Classifier: Topic :: Multimedia :: Graphics
Classifier: License :: OSI Approved :: MIT License
Classifier: Operating System :: OS Independent
Requires-Python: >=3.10
License-File: LICENSE
Requires-Dist: manim>=0.19.0
Requires-Dist: numpy>=1.24
Dynamic: author
Dynamic: classifier
Dynamic: description
Dynamic: description-content-type
Dynamic: home-page
Dynamic: license
Dynamic: license-file
Dynamic: requires-dist
Dynamic: requires-python
Dynamic: summary
